<?xml version="1.0" encoding="UTF-8"?>
<con:resource name="Admin_deactivateUser" path="/xs1/api/users/{userid}/active" id="dfbf8f10-796f-4150-9397-f6e18b4332fa" xmlns:xsi="http://www.w3.org/2001/XMLSchema-instance" xmlns:con="http://eviware.com/soapui/config">
  <con:settings>
    <con:setting id="dfbf8f10-796f-4150-9397-f6e18b4332fafileName">Admin_deactivateUser</con:setting>
  </con:settings>
  <con:parameters>
    <con:parameter>
      <con:name>X-XSRF-TOKEN</con:name>
      <con:value/>
      <con:style>HEADER</con:style>
      <con:default/>
      <con:description xsi:nil="true"/>
    </con:parameter>
    <con:parameter>
      <con:name>Cookie</con:name>
      <con:value/>
      <con:style>HEADER</con:style>
      <con:default/>
      <con:description xsi:nil="true"/>
    </con:parameter>
    <con:parameter>
      <con:name>userid</con:name>
      <con:style>TEMPLATE</con:style>
    </con:parameter>
  </con:parameters>
  <con:method name="deactivateUser" id="5b91d2e1-ffc4-4254-a61f-7d69ac99e380" method="PUT">
    <con:settings/>
    <con:parameters/>
    <con:representation type="REQUEST">
      <con:mediaType>application/json</con:mediaType>
      <con:params/>
    </con:representation>
    <con:representation type="RESPONSE">
      <con:mediaType>application/json;charset=UTF-8</con:mediaType>
      <con:status>200</con:status>
      <con:params/>
      <con:element xmlns:act="https://xs1qa2.xypro.com/xs1/api/users/213/active">act:Response</con:element>
    </con:representation>
    <con:representation type="FAULT">
      <con:mediaType>application/json;charset=UTF-8</con:mediaType>
      <con:status>400 500</con:status>
      <con:params/>
      <con:element xmlns:act="https://xs1qa2.xypro.com/xs1/api/users/213/active">act:Fault</con:element>
    </con:representation>
    <con:request name="Request 1" id="c42c312c-b9b2-4f68-a169-31be13b0ff79" mediaType="application/json" postQueryString="false">
      <con:settings/>
      <con:endpoint>https://xs1qa3.xypro.com</con:endpoint>
      <con:request/>
      <con:credentials>
        <con:selectedAuthProfile>No Authorization</con:selectedAuthProfile>
        <con:authType>No Authorization</con:authType>
      </con:credentials>
      <con:jmsConfig JMSDeliveryMode="PERSISTENT"/>
      <con:parameters>
        <con:entry key="Cookie" value="${#Project#cookie} "/>
        <con:entry key="X-XSRF-TOKEN" value="${#Project#token} "/>
        <con:entry key="userid" value="${#Project#currentUserId}"/>
      </con:parameters>
      <con:parameterOrder>
        <con:entry>Cookie</con:entry>
        <con:entry>userid</con:entry>
        <con:entry>X-XSRF-TOKEN</con:entry>
      </con:parameterOrder>
      <con:environmentSpec>
        <con:entry environmentId="b0ce29d2-283a-41b3-afc3-a97507050086">
          <con:authProfile>No Authorization</con:authProfile>
        </con:entry>
        <con:entry environmentId="375b6235-a7ab-438f-82f7-e243e92b9dd0">
          <con:authProfile>Inherit From Parent</con:authProfile>
        </con:entry>
        <con:entry environmentId="1acccb02-b4b7-4e89-ae4b-e82d2719f308">
          <con:authProfile>Inherit From Parent</con:authProfile>
        </con:entry>
      </con:environmentSpec>
    </con:request>
    <con:environmentSpec>
      <con:entry environmentId="1acccb02-b4b7-4e89-ae4b-e82d2719f308">
        <con:authProfile>Inherit From Parent</con:authProfile>
      </con:entry>
    </con:environmentSpec>
  </con:method>
  <con:environmentSpec>
    <con:entry environmentId="1acccb02-b4b7-4e89-ae4b-e82d2719f308">
      <con:authProfile>Inherit From Parent</con:authProfile>
    </con:entry>
  </con:environmentSpec>
</con:resource>
